smith/__init__.py
smith/api.py
smith/cli.py
smith/scapy_wrapper.py
smith/wsgiref_wrapper.py
smith-0.0.1.dist-info/DESCRIPTION.rst
smith-0.0.1.dist-info/METADATA
smith-0.0.1.dist-info/RECORD
smith-0.0.1.dist-info/WHEEL
smith-0.0.1.dist-info/entry_points.txt
smith-0.0.1.dist-info/metadata.json
smith-0.0.1.dist-info/top_level.txt
