Metadata-Version: 2.0
Name: smith
Version: 0.0.1
Summary: An agent that can act as either a client or a server for testing connectivity between two machines on a network.
Home-page: UNKNOWN
Author: UNKNOWN
Author-email: UNKNOWN
License: UNKNOWN
Platform: UNKNOWN
